portus/__init__.py
portus/adapters/__init__.py
portus/adapters/input/__init__.py
portus/adapters/input/rest_controller/__init__.py
portus/adapters/input/rest_controller/controller.py
portus/adapters/input/rest_controller/config/__init__.py
portus/adapters/input/rest_controller/config/metadata.py
portus/adapters/output/__init__.py
portus/adapters/output/notifications.py
portus/adapters/output/in_memory/__init__.py
portus/adapters/output/in_memory/base.py
portus/adapters/output/in_memory/related_repo_base.py
portus/adapters/output/mongodb/__init__.py
portus/adapters/output/mongodb/base.py
portus/adapters/output/mongodb/crud.py
portus/adapters/output/mongodb/related.py
portus/adapters/output/sqlalchemy/__init__.py
portus/adapters/output/sqlalchemy/base.py
portus/adapters/output/sqlalchemy/crud.py
portus/adapters/output/sqlalchemy/related.py
portus/common/__init__.py
portus/common/context_schemas.py
portus/common/internal_data.py
portus/common/logger.py
portus/common/types.py
portus/common/exceptions/__init__.py
portus/common/exceptions/repository.py
portus/common/exceptions/transformation.py
portus/common/exceptions/triggers.py
portus/common/exceptions/validation.py
portus/core/__init__.py
portus/core/services/__init__.py
portus/core/services/advanced.py
portus/core/services/crud.py
portus/core/services/default.py
portus/hooks/__init__.py
portus/hooks/base/__init__.py
portus/hooks/base/hook.py
portus/hooks/base/orchestrator.py
portus/hooks/relation/__init__.py
portus/hooks/relation/setter.py
portus/hooks/relation/validator.py
portus/hooks/transformer/__init__.py
portus/hooks/transformer/core.py
portus/hooks/transformer/predefined.py
portus/hooks/triggerer/__init__.py
portus/hooks/triggerer/core.py
portus/hooks/triggerer/predefined.py
portus/hooks/validator/__init__.py
portus/hooks/validator/core.py
portus/hooks/validator/predefined.py
portus/mappers/__init__.py
portus/mappers/base.py
portus/mappers/db_base.py
portus/mappers/db_default.py
portus/mappers/default.py
portus_core-0.1.0.dist-info/licenses/AUTHORS.rst
portus_core-0.1.0.dist-info/licenses/LICENSE.TXT
portus_core-0.1.0.dist-info/METADATA
portus_core-0.1.0.dist-info/WHEEL
portus_core-0.1.0.dist-info/top_level.txt
portus_core-0.1.0.dist-info/RECORD
