Metadata-Version: 2.4
Name: portus-core
Version: 0.1.0
Summary: A hexagonal‑architecture service framework for Python
Author-email: Carlos Pérez Küper <carlosperezkuper@email.com>
Project-URL: Homepage, https://github.com/charlyperezk/portus
Project-URL: Repository, https://github.com/charlyperezk/portus.git
License-File: LICENSE.TXT
License-File: AUTHORS.rst
Requires-Dist: pydantic>=2.0
Requires-Dist: argon2>=0.1.10
Requires-Dist: argon2-cffi>=21.3.0
Requires-Dist: colorlog>=6.9.0
Requires-Dist: fastapi>=0.115.12
Requires-Dist: loguru>=0.7.3
Requires-Dist: pydantic>=2.11.4
Requires-Dist: pytest>=8.3.5
Requires-Dist: pydantic[email]
Requires-Dist: uvicorn[standard]
Requires-Dist: sqlalchemy>=2.0.20
Requires-Dist: sqlalchemy[asyncio]>=2.0.20
Requires-Dist: aiosqlite>=0.17.0
Requires-Dist: pymongo>=4.12.1
Requires-Dist: motor>=3.7.0
Requires-Dist: beanie>=1.29.0
Provides-Extra: dev
Requires-Dist: pytest; extra == "dev"
Requires-Dist: pytest-asyncio; extra == "dev"
Requires-Dist: black; extra == "dev"
Requires-Dist: isort; extra == "dev"
Dynamic: license-file
